{
  "name": "jsg:stargate/parts/milkyway/ramp_fronts/mangrove",
  "fallback": "minecraft:empty",
  "elements": [
    {
      "weight": 1,
      "element": {
        "element_type": "minecraft:single_pool_element",
        "projection": "rigid",
        "location": "jsg:stargate/parts/milkyway/generic/wet_biomes/fronts/front_1",
        "processors": "jsg:stargate_outpost/mangrove"
      }
    },
    {
      "weight": 1,
      "element": {
        "element_type": "minecraft:single_pool_element",
        "projection": "rigid",
        "location": "jsg:stargate/parts/milkyway/generic/wet_biomes/fronts/front_2",
        "processors": "jsg:stargate_outpost/mangrove"
      }
    },
    {
      "weight": 1,
      "element": {
        "element_type": "minecraft:single_pool_element",
        "projection": "rigid",
        "location": "jsg:stargate/parts/milkyway/generic/wet_biomes/fronts/front_3",
        "processors": "jsg:stargate_outpost/mangrove"
      }
    },
    {
      "weight": 1,
      "element": {
        "element_type": "minecraft:single_pool_element",
        "projection": "rigid",
        "location": "jsg:stargate/parts/milkyway/generic/wet_biomes/fronts/front_4",
        "processors": "jsg:stargate_outpost/mangrove"
      }
    }
  ]
}