{
  "name": "jsg:abydos/cartouche/braziers",
  "fallback": "minecraft:empty",
  "elements": [
    {
      "weight": 2,
      "element": {
        "location": "jsg:abydos/brazier_on",
        "processors": "minecraft:empty",
        "projection": "rigid",
        "element_type": "minecraft:single_pool_element"
      }
    },
    {
      "weight": 1,
      "element": {
        "location": "jsg:abydos/brazier_off",
        "processors": "minecraft:empty",
        "projection": "rigid",
        "element_type": "minecraft:single_pool_element"
      }
    }
  ]
}